{
  "id": "10.17913/bgtl/2002/5/Hara_CA",
  "type": "dois",
  "attributes": {
    "creators": [
      {
        "nameType": "personal",
        "given_name": "C. A.",
        "family_name": "Hara",
        "affiliation": [
          {
            "name": "University of California, Berkeley",
            "affiliationIdentifier": "https://ror.org/01an7q238",
            "affiliationIdentifierScheme": "ROR"
          }
        ]
      }
    ],
    "contributors": [
      {
        "nameType": "personal",
        "given_name": "C. A.",
        "family_name": "Hara",
        "affiliation": [
          {
            "name": "University of California, Berkeley",
            "affiliationIdentifier": "https://ror.org/01an7q238",
            "affiliationIdentifierScheme": "ROR"
          }
        ],
        "contributorType": "RightsHolder"
      },
      [
        {
          "nameType": "organizational",
          "name": "Gump South Pacific Research Station",
          "affiliation": [
            {
              "name": "Gump South Pacific Research Station",
              "affiliationIdentifier": "https://ror.org/04sk0et52",
              "affiliationIdentifierScheme": "ROR",
              "lang": "en"
            }
          ],
          "contributorType": "Sponsor",
          "nameIdentifiers": [
            {
              "nameIdentifier": "https://ror.org/04sk0et52",
              "nameIdentifierScheme": "ROR"
            }
          ]
        }
      ]
    ],
    "descriptions": [
      {
        "lang": "en",
        "description": "The blacktip reef shark, Carcharhinus melanopterus, was observed in response to feeding stimuli in Mo\u201a\u00c4\u00f6\u221a\u00d1\u221a\u00a5orea, French Polynesia. Natural abundance, abundance in response to feeding stimuli and abundance prior to tour boat arrival were observed at two established sites(1,2), and a third newly established site(3). The arrival time of C. melanopterus prior to food stimuli in the water was also observed in order to determine if the tour boat acted as an attractant. Interactions between time of day and shark abundance were compared with one another to determine if a significant interaction occurred at each site. Statistical analysis showed that time of day and site were significant indicators of abundace at established sites, but not at a newly established site. The data also indicate that at established sites a slight increase in abundance occurred prior to boat arrival, but it was not statistically significant. Statistical analysis of C. melanopterus arrival times at sites 1,2 and 3, and found that sites 1 and 2 were more similar than site 3, which did not have a response from C. melanopterus to food stimuli, time of day, or boat stimuli. Arrival prior to food placement in the water at sites 1 and 2 was observed and introduces the possibility that the sharks may be responding to the cue of boat presence, and not only food stimuli. The lack of response to stimuli at site 3 in contrast with the behaviors shown at sites 1 and 2 suggests that the natural behavior of C. melanopterus has been altered to an extent at established sites.",
        "descriptionType": "Abstract"
      }
    ],
    "title": [
      {
        "lang": "en",
        "title": "Abundance and Response of Carcharhinus melanopterus to Feeding Stimuli in Mo\u201a\u00c4\u00f6\u221a\u00d1\u221a\u00a5orea, French Polynesia"
      }
    ],
    "publicationYear": "2002",
    "publisher": {
      "name": "University of California, Berkeley",
      "publisherIdentifier": "https://ror.org/01an7q238",
      "publisherIdentifierScheme": "ROR",
      "lang": "en"
    },
    "dates": [
      [
        {
          "date": "2002",
          "dateType": "Copyrighted"
        }
      ]
    ],
    "types": [
      {
        "resourceTypeGeneral": "Preprint"
      }
    ],
    "subjects": [
      {
        "subject": "Carcharhinus melanopterus"
      },
      {
        "subject": "Chondrichthyes"
      },
      {
        "subject": "Carcharhinidae"
      },
      {
        "subject": "shark feeding"
      },
      {
        "subject": "behavior"
      },
      {
        "subject": "Mo\u201a\u00c4\u00f6\u221a\u00d1\u221a\u00a5orea"
      },
      {
        "subject": "French Polynesia"
      },
      {
        "subject": "fish",
        "subjectScheme": "organism"
      }
    ],
    "geoLocations": [
      {
        "geoLocationPlace": "marine"
      }
    ],
    "related_identifiers": [
      {
        "relatedIdentifier": "ProjectIdentifierFor2002",
        "relationType": "IsPartOf",
        "resourceTypeGeneral": "Project",
        "relatedIdentifierType": "DOI"
      }
    ],
    "version": 1,
    "rightsList": [
      [
        {
          "rights": "Creative Commons Attribution 4.0 International",
          "rightsUri": "https://creativecommons.org/licenses/by/4.0/legalcode",
          "schemeUri": "https://spdx.org/licenses/",
          "rightsIdentifier": "cc-by-4.0",
          "rightsIdentifierScheme": "SPDX"
        }
      ]
    ]
  }
}