{
  "id": "10.17913/bgtl/2019/7/Hallsten_Molly",
  "type": "dois",
  "attributes": {
    "creators": [
      {
        "nameType": "personal",
        "given_name": "Molly",
        "family_name": "Hallsten",
        "affiliation": [
          {
            "name": "University of California, Berkeley",
            "affiliationIdentifier": "https://ror.org/01an7q238",
            "affiliationIdentifierScheme": "ROR"
          }
        ]
      }
    ],
    "contributors": [
      {
        "nameType": "personal",
        "given_name": "Molly",
        "family_name": "Hallsten",
        "affiliation": [
          {
            "name": "University of California, Berkeley",
            "affiliationIdentifier": "https://ror.org/01an7q238",
            "affiliationIdentifierScheme": "ROR"
          }
        ],
        "contributorType": "RightsHolder"
      },
      [
        {
          "nameType": "organizational",
          "name": "Gump South Pacific Research Station",
          "affiliation": [
            {
              "name": "Gump South Pacific Research Station",
              "affiliationIdentifier": "https://ror.org/04sk0et52",
              "affiliationIdentifierScheme": "ROR",
              "lang": "en"
            }
          ],
          "contributorType": "Sponsor",
          "nameIdentifiers": [
            {
              "nameIdentifier": "https://ror.org/04sk0et52",
              "nameIdentifierScheme": "ROR"
            }
          ]
        }
      ]
    ],
    "title": [
      {
        "lang": "en",
        "title": "Size-based dominance hierarchy in one of two sympatric cryptic pacific skinks (Emoia impar and Emoia cyanura)"
      }
    ],
    "publicationYear": "2019",
    "publisher": {
      "name": "University of California, Berkeley",
      "publisherIdentifier": "https://ror.org/01an7q238",
      "publisherIdentifierScheme": "ROR",
      "lang": "en"
    },
    "dates": [
      [
        {
          "date": "2019",
          "dateType": "Copyrighted"
        }
      ]
    ],
    "types": [
      {
        "resourceTypeGeneral": "Preprint"
      }
    ],
    "related_identifiers": [
      {
        "relatedIdentifier": "ProjectIdentifierFor2019",
        "relationType": "IsPartOf",
        "resourceTypeGeneral": "Project",
        "relatedIdentifierType": "DOI"
      }
    ],
    "version": 1,
    "rightsList": [
      [
        {
          "rights": "Creative Commons Attribution 4.0 International",
          "rightsUri": "https://creativecommons.org/licenses/by/4.0/legalcode",
          "schemeUri": "https://spdx.org/licenses/",
          "rightsIdentifier": "cc-by-4.0",
          "rightsIdentifierScheme": "SPDX"
        }
      ]
    ]
  }
}