{
  "id": "10.17913/bgtl/2012/21/Wu_JasperG",
  "type": "dois",
  "attributes": {
    "creators": [
      {
        "nameType": "personal",
        "given_name": "Jasper G.",
        "family_name": "Wu",
        "affiliation": [
          {
            "name": "University of California, Berkeley",
            "affiliationIdentifier": "https://ror.org/01an7q238",
            "affiliationIdentifierScheme": "ROR"
          }
        ]
      }
    ],
    "contributors": [
      {
        "nameType": "personal",
        "given_name": "Jasper G.",
        "family_name": "Wu",
        "affiliation": [
          {
            "name": "University of California, Berkeley",
            "affiliationIdentifier": "https://ror.org/01an7q238",
            "affiliationIdentifierScheme": "ROR"
          }
        ],
        "contributorType": "RightsHolder"
      },
      [
        {
          "nameType": "organizational",
          "name": "Gump South Pacific Research Station",
          "affiliation": [
            {
              "name": "Gump South Pacific Research Station",
              "affiliationIdentifier": "https://ror.org/04sk0et52",
              "affiliationIdentifierScheme": "ROR",
              "lang": "en"
            }
          ],
          "contributorType": "Sponsor",
          "nameIdentifiers": [
            {
              "nameIdentifier": "https://ror.org/04sk0et52",
              "nameIdentifierScheme": "ROR"
            }
          ]
        }
      ]
    ],
    "title": [
      {
        "lang": "en",
        "title": "The composition of bryophyte comunities on limestone versus basalt substrates in coastal and mid-elevation forests of Mo'orea, French Polynesia"
      }
    ],
    "publicationYear": "2012",
    "publisher": {
      "name": "University of California, Berkeley",
      "publisherIdentifier": "https://ror.org/01an7q238",
      "publisherIdentifierScheme": "ROR",
      "lang": "en"
    },
    "dates": [
      [
        {
          "date": "2012",
          "dateType": "Copyrighted"
        }
      ]
    ],
    "types": [
      {
        "resourceTypeGeneral": "Preprint"
      }
    ],
    "subjects": [
      {
        "subject": "Mo'orea, French Polynesia"
      },
      {
        "subject": "plants"
      },
      {
        "subject": "bryophyte"
      },
      {
        "subject": "bioindicators"
      },
      {
        "subject": "abiotic"
      },
      {
        "subject": "substrate"
      },
      {
        "subject": "limestone"
      },
      {
        "subject": "basalt"
      },
      {
        "subject": "soil pH"
      },
      {
        "subject": "buffering capacity"
      },
      {
        "subject": "phosphate"
      },
      {
        "subject": "water"
      },
      {
        "subject": "distribution"
      },
      {
        "subject": "Ectropothecium sandwichense"
      },
      {
        "subject": "Floribundaria aerunginosa"
      },
      {
        "subject": "Calymperes aongstroemii"
      },
      {
        "subject": "Taxithelium vernieri"
      },
      {
        "subject": "Ectropothecium sodale"
      },
      {
        "subject": "plant",
        "subjectScheme": "organism"
      }
    ],
    "geoLocations": [
      {
        "geoLocationPlace": "terrestrial"
      }
    ],
    "related_identifiers": [
      {
        "relatedIdentifier": "ProjectIdentifierFor2012",
        "relationType": "IsPartOf",
        "resourceTypeGeneral": "Project",
        "relatedIdentifierType": "DOI"
      }
    ],
    "version": 1,
    "rightsList": [
      [
        {
          "rights": "Creative Commons Attribution 4.0 International",
          "rightsUri": "https://creativecommons.org/licenses/by/4.0/legalcode",
          "schemeUri": "https://spdx.org/licenses/",
          "rightsIdentifier": "cc-by-4.0",
          "rightsIdentifierScheme": "SPDX"
        }
      ]
    ]
  }
}